{
    "name": "NuHeat",
    "docs": "https://github.com/simplextech/udi-poly-nuheat",
    "type": "python3",
    "executable": "nuheat.py",
    "install_cloud": "install_cloud.sh",
    "description": "A NodeServer for the NuHeat Signature Thermostat",
    "notice": "In Development - Use at your own risk",
    "shortPoll": "120",
    "longPoll": "1800",
    "testMode": true,
    "profile_version": "0.0.23",
    "credits": [
        {
            "title": "NuHeat: A NodeServer for the NuHeat Signature Thermostat",
            "author": "Simplex Technology",
            "version": "0.0.23",
            "date": "November 21, 2019",
            "source": "https://github.com/simplextech/udi-poly-nuheat",
            "license": "https://github.com/simplextech/udi-poly-nuheat/blob/master/LICENSE"
        }
    ]
}
